LICENSE
README.md
setup.cfg
setup.py
Fishconsole/Fishconsole_version_a.py
Fishconsole/Fishconsole_version_b.py
Fishconsole/Fishsys.py
Fishconsole/__init__.py
Fishconsole/fcv.py
Fishconsole/files.py
Fishconsole/helps.py
Fishconsole/houtai.py
Fishconsole/huitu.py
Fishconsole/logs.py
Fishconsole/window.py
Fishconsole.egg-info/PKG-INFO
Fishconsole.egg-info/SOURCES.txt
Fishconsole.egg-info/dependency_links.txt
Fishconsole.egg-info/requires.txt
Fishconsole.egg-info/top_level.txt