Metadata-Version: 2.1
Name: Fishconsole
Version: 3.0.6
Summary: 一个有点东西的工具合集，代码上不是很规范，用起来很实在，长期更新（虽然会有bug）
Home-page: https://space.bilibili.com/698117971?spm_id_from=333.1007.0.0
Author: Fish Console
Author-email: 2645602049@qq.com
License: UNKNOWN
Platform: UNKNOWN
License-File: LICENSE
